{"title":"FOD - Sport & Vrije tijd - Brussel P1","url":"https://finshop.belgium.be/nl_BE/shop?type=auction&finshop=3&category_select=1&state=&keyword=","favicon":"https://finshop.belgium.be/nl_BE/favicon.ico","elements":[{"title":"Lot 1171 Opel Corsa-E - 157.288 Km - Diesel EURO 6b","contents":"<div class=\"o_wsale_product_grid_wrapper o_wsale_product_grid_wrapper_1_1\">\n        <form action=\"/nl_BE/shop/cart/update\" method=\"post\" class=\"card oe_product_cart\" itemscope=\"itemscope\" itemtype=\"http://schema.org/Product\" data-publish=\"on\" id=\"product-28669\" title=\"Lot 1171 Opel Corsa-E - 157.288 Km - Diesel EURO 6b\">\n            <a class=\"o_product_link css_editable_mode_hidden\" href=\"/nl_BE/shop/bxl-00495-1-11781-1-lot-1171-opel-corsa-e-157-288-km-diesel-euro-6b-28669\"></a>\n            <div class=\"card-body p-1 oe_product_image\">\n                <input type=\"hidden\" name=\"csrf_token\" value=\"b9e7ff1167226ba50037530fda32a27e197cf42ao1755624793\">\n                <a class=\"d-block h-100\" itemprop=\"url\" href=\"/nl_BE/shop/bxl-00495-1-11781-1-lot-1171-opel-corsa-e-157-288-km-diesel-euro-6b-28669\">\n                    <span class=\"d-flex h-100 justify-content-center align-items-center\"><img src=\"/web/image/product.template/28669/image_256/%5BBXL-00495-1-11781-1%5D%20Lot%201171%20Opel%20Corsa-E%20-%20157.288%20Km%20-%20Diesel%20EURO%206b?unique=ff97b72\" itemprop=\"image\" class=\"img img-fluid\" alt=\"[BXL/00495/1/11781/1] Lot 1171 Opel Corsa-E - 157.288 Km - Diesel EURO 6b\" loading=\"lazy\"></span>\n                </a>\n          <div class=\"product_item auction_running\">\n            <div class=\"col-md-12 card-header border countdown\" style=\"padding:0px\" data-wk_time_left=\"2024-08-22 16:00:00\" data-wk_auction_state=\"running\">\n              <div class=\"row auction_timer\">\n          <div class=\"col-3 text-center\">\n            <span class=\"days span_time_digit\">02</span>\n            <br>\n                        <span class=\"span_time_unit\">Dagen</span>\n          </div>\n          <div class=\"col-3 text-center\">\n            <span class=\"hours span_time_digit\">22</span>\n            <br>\n                        <span class=\"span_time_unit\">Uren</span>\n          </div>\n          <div class=\"col-3 text-center\">\n            <span class=\"minutes span_time_digit\">26</span>\n            <br>\n                        <span class=\"span_time_unit\">Minuten</span>\n          </div>\n          <div class=\"col-3 text-center\">\n            <span class=\"seconds span_time_digit\">46</span>\n            <br>\n                        <span class=\"span_time_unit\">Seconden</span>\n          </div>\n        </div>\n            </div>\n          </div>\n        <div class=\"product_item-warehouse\">\n          <p>Finshop\n            <span class=\"font-weight-bold d-block\">Brussel</span>\n          </p>\n        </div>\n      </div>\n            <div class=\"card-body p-0 o_wsale_product_information\">\n                <div class=\"p-2 o_wsale_product_information_text\">\n                    <h6 class=\"o_wsale_products_item_title mb-1\">\n                        <a class=\"text-primary text-decoration-none text-truncate-2-lines\" itemprop=\"name\" href=\"/nl_BE/shop/bxl-00495-1-11781-1-lot-1171-opel-corsa-e-157-288-km-diesel-euro-6b-28669\" content=\"Lot 1171 Opel Corsa-E - 157.288 Km - Diesel EURO 6b\">Lot 1171 Opel Corsa-E - 157.288 Km - Diesel EURO 6b</a>\n                    </h6>\n           <div class=\"text-info oe_subdescription\" contenteditable=\"false\">\n           </div>\n            <p>\n                <span class=\"col-md-4\" style=\"padding-left:0px;padding-right:0px\">\n                  <a class=\"span_total_bids\" href=\"/nl_BE/product/auction/24871\">\n                    2 Biedingen</a>\n                </span>\n                <span style=\"padding-left:0px;padding-right:0px\" class=\"col-md-8 category_page_timer auction_running\">\n                      <span class=\"span_time_digit\">02</span><span class=\"span_time_unit\">d. </span><span class=\"span_time_digit\">22</span><span class=\"span_time_unit\">h. </span><span class=\"span_time_digit\">26</span><span class=\"span_time_unit\">m. </span><span class=\"span_time_digit\">47</span><span class=\"span_time_unit\">s. </span>\n                      <span>&nbsp;&nbsp; left</span>\n                </span>\n                </p><div style=\"position: absolute; bottom: 0; padding: 5px 0; font-size: 14px;\">\n                  <b>\n                    Huidig bod €&nbsp;<span class=\"oe_currency_value\">3.050,00</span>\n                  </b>\n                </div>\n           <p></p>\n      </div>\n                <div class=\"o_wsale_product_btn pl-2\"></div>\n            </div>\n            <span class=\"o_ribbon \" style=\"\"></span>\n        </form>\n                                                        </div>","link":"https://finshop.belgium.be/nl_BE/shop/bxl-00495-1-11781-1-lot-1171-opel-corsa-e-157-288-km-diesel-euro-6b-28669","retrieved":1724088794543},{"title":"Lot 1283 Mitsubishi Outlander - 154.410 Km - Benzine + elec. EURO 5b","contents":"<div class=\"o_wsale_product_grid_wrapper o_wsale_product_grid_wrapper_1_1\">\n        <form action=\"/nl_BE/shop/cart/update\" method=\"post\" class=\"card oe_product_cart\" itemscope=\"itemscope\" itemtype=\"http://schema.org/Product\" data-publish=\"on\" id=\"product-28672\" title=\"Lot 1283 Mitsubishi Outlander - 154.410 Km - Benzine + elec. EURO 5b\">\n            <a class=\"o_product_link css_editable_mode_hidden\" href=\"/nl_BE/shop/bxl-01704-1-11782-1-lot-1283-mitsubishi-outlander-154-410-km-benzine-elec-euro-5b-28672\"></a>\n            <div class=\"card-body p-1 oe_product_image\">\n                <input type=\"hidden\" name=\"csrf_token\" value=\"b9e7ff1167226ba50037530fda32a27e197cf42ao1755624793\">\n                <a class=\"d-block h-100\" itemprop=\"url\" href=\"/nl_BE/shop/bxl-01704-1-11782-1-lot-1283-mitsubishi-outlander-154-410-km-benzine-elec-euro-5b-28672\">\n                    <span class=\"d-flex h-100 justify-content-center align-items-center\"><img src=\"/web/image/product.template/28672/image_256/%5BBXL-01704-1-11782-1%5D%20Lot%201283%20Mitsubishi%20Outlander%20-%20154.410%20Km%20-%20Benzine%20%2B%20elec.%20EURO%205b?unique=c6f3d14\" itemprop=\"image\" class=\"img img-fluid\" alt=\"[BXL/01704/1/11782/1] Lot 1283 Mitsubishi Outlander - 154.410 Km - Benzine + elec. EURO 5b\" loading=\"lazy\"></span>\n                </a>\n          <div class=\"product_item auction_running\">\n            <div class=\"col-md-12 card-header border countdown\" style=\"padding:0px\" data-wk_time_left=\"2024-08-22 16:05:00\" data-wk_auction_state=\"running\">\n              <div class=\"row auction_timer\">\n          <div class=\"col-3 text-center\">\n            <span class=\"days span_time_digit\">02</span>\n            <br>\n                        <span class=\"span_time_unit\">Dagen</span>\n          </div>\n          <div class=\"col-3 text-center\">\n            <span class=\"hours span_time_digit\">22</span>\n            <br>\n                        <span class=\"span_time_unit\">Uren</span>\n          </div>\n          <div class=\"col-3 text-center\">\n            <span class=\"minutes span_time_digit\">31</span>\n            <br>\n                        <span class=\"span_time_unit\">Minuten</span>\n          </div>\n          <div class=\"col-3 text-center\">\n            <span class=\"seconds span_time_digit\">46</span>\n            <br>\n                        <span class=\"span_time_unit\">Seconden</span>\n          </div>\n        </div>\n            </div>\n          </div>\n        <div class=\"product_item-warehouse\">\n          <p>Finshop\n            <span class=\"font-weight-bold d-block\">Brussel</span>\n          </p>\n        </div>\n      </div>\n            <div class=\"card-body p-0 o_wsale_product_information\">\n                <div class=\"p-2 o_wsale_product_information_text\">\n                    <h6 class=\"o_wsale_products_item_title mb-1\">\n                        <a class=\"text-primary text-decoration-none text-truncate-2-lines\" itemprop=\"name\" href=\"/nl_BE/shop/bxl-01704-1-11782-1-lot-1283-mitsubishi-outlander-154-410-km-benzine-elec-euro-5b-28672\" content=\"Lot 1283 Mitsubishi Outlander - 154.410 Km - Benzine + elec. EURO 5b\">Lot 1283 Mitsubishi Outlander - 154.410 Km - Benzine + elec. EURO 5b</a>\n                    </h6>\n           <div class=\"text-info oe_subdescription\" contenteditable=\"false\">\n           </div>\n            <p>\n                <span class=\"col-md-4\" style=\"padding-left:0px;padding-right:0px\">\n                  <a class=\"span_total_bids\" href=\"/nl_BE/product/auction/24873\">\n                    3 Biedingen</a>\n                </span>\n                <span style=\"padding-left:0px;padding-right:0px\" class=\"col-md-8 category_page_timer auction_running\">\n                      <span class=\"span_time_digit\">02</span><span class=\"span_time_unit\">d. </span><span class=\"span_time_digit\">22</span><span class=\"span_time_unit\">h. </span><span class=\"span_time_digit\">31</span><span class=\"span_time_unit\">m. </span><span class=\"span_time_digit\">47</span><span class=\"span_time_unit\">s. </span>\n                      <span>&nbsp;&nbsp; left</span>\n                </span>\n                </p><div style=\"position: absolute; bottom: 0; padding: 5px 0; font-size: 14px;\">\n                  <b>\n                    Huidig bod €&nbsp;<span class=\"oe_currency_value\">6.300,00</span>\n                  </b>\n                </div>\n           <p></p>\n      </div>\n                <div class=\"o_wsale_product_btn pl-2\"></div>\n            </div>\n            <span class=\"o_ribbon \" style=\"\"></span>\n        </form>\n                                                        </div>","link":"https://finshop.belgium.be/nl_BE/shop/bxl-01704-1-11782-1-lot-1283-mitsubishi-outlander-154-410-km-benzine-elec-euro-5b-28672","retrieved":1724088794545},{"title":"Lot 1221 Nissan Primastar - 67.012 Km - Diesel EURO 6if","contents":"<div class=\"o_wsale_product_grid_wrapper o_wsale_product_grid_wrapper_1_1\">\n        <form action=\"/nl_BE/shop/cart/update\" method=\"post\" class=\"card oe_product_cart\" itemscope=\"itemscope\" itemtype=\"http://schema.org/Product\" data-publish=\"on\" id=\"product-28673\" title=\"Lot 1221 Nissan Primastar - 67.012 Km - Diesel EURO 6if\">\n            <a class=\"o_product_link css_editable_mode_hidden\" href=\"/nl_BE/shop/bxl-01705-2-11783-1-lot-1221-nissan-primastar-67-012-km-diesel-euro-6if-28673\"></a>\n            <div class=\"card-body p-1 oe_product_image\">\n                <input type=\"hidden\" name=\"csrf_token\" value=\"b9e7ff1167226ba50037530fda32a27e197cf42ao1755624793\">\n                <a class=\"d-block h-100\" itemprop=\"url\" href=\"/nl_BE/shop/bxl-01705-2-11783-1-lot-1221-nissan-primastar-67-012-km-diesel-euro-6if-28673\">\n                    <span class=\"d-flex h-100 justify-content-center align-items-center\"><img src=\"/web/image/product.template/28673/image_256/%5BBXL-01705-2-11783-1%5D%20Lot%201221%20Nissan%20Primastar%20-%2067.012%20Km%20-%20Diesel%20EURO%206if?unique=44ef4a3\" itemprop=\"image\" class=\"img img-fluid\" alt=\"[BXL/01705/2/11783/1] Lot 1221 Nissan Primastar - 67.012 Km - Diesel EURO 6if\" loading=\"lazy\"></span>\n                </a>\n          <div class=\"product_item auction_running\">\n            <div class=\"col-md-12 card-header border countdown\" style=\"padding:0px\" data-wk_time_left=\"2024-08-22 16:10:00\" data-wk_auction_state=\"running\">\n              <div class=\"row auction_timer\">\n          <div class=\"col-3 text-center\">\n            <span class=\"days span_time_digit\">02</span>\n            <br>\n                        <span class=\"span_time_unit\">Dagen</span>\n          </div>\n          <div class=\"col-3 text-center\">\n            <span class=\"hours span_time_digit\">22</span>\n            <br>\n                        <span class=\"span_time_unit\">Uren</span>\n          </div>\n          <div class=\"col-3 text-center\">\n            <span class=\"minutes span_time_digit\">36</span>\n            <br>\n                        <span class=\"span_time_unit\">Minuten</span>\n          </div>\n          <div class=\"col-3 text-center\">\n            <span class=\"seconds span_time_digit\">46</span>\n            <br>\n                        <span class=\"span_time_unit\">Seconden</span>\n          </div>\n        </div>\n            </div>\n          </div>\n        <div class=\"product_item-warehouse\">\n          <p>Finshop\n            <span class=\"font-weight-bold d-block\">Brussel</span>\n          </p>\n        </div>\n      </div>\n            <div class=\"card-body p-0 o_wsale_product_information\">\n                <div class=\"p-2 o_wsale_product_information_text\">\n                    <h6 class=\"o_wsale_products_item_title mb-1\">\n                        <a class=\"text-primary text-decoration-none text-truncate-2-lines\" itemprop=\"name\" href=\"/nl_BE/shop/bxl-01705-2-11783-1-lot-1221-nissan-primastar-67-012-km-diesel-euro-6if-28673\" content=\"Lot 1221 Nissan Primastar - 67.012 Km - Diesel EURO 6if\">Lot 1221 Nissan Primastar - 67.012 Km - Diesel EURO 6if</a>\n                    </h6>\n           <div class=\"text-info oe_subdescription\" contenteditable=\"false\">\n           </div>\n            <p>\n                <span class=\"col-md-4\" style=\"padding-left:0px;padding-right:0px\">\n                  <a class=\"span_total_bids\" href=\"/nl_BE/product/auction/24874\">\n                    0 Biedingen</a>\n                </span>\n                <span style=\"padding-left:0px;padding-right:0px\" class=\"col-md-8 category_page_timer auction_running\">\n                      <span class=\"span_time_digit\">02</span><span class=\"span_time_unit\">d. </span><span class=\"span_time_digit\">22</span><span class=\"span_time_unit\">h. </span><span class=\"span_time_digit\">36</span><span class=\"span_time_unit\">m. </span><span class=\"span_time_digit\">47</span><span class=\"span_time_unit\">s. </span>\n                      <span>&nbsp;&nbsp; left</span>\n                </span>\n                </p><div style=\"position: absolute; bottom: 0; padding: 5px 0; font-size: 14px;\">\n                  <b>\n                    Huidig bod €&nbsp;<span class=\"oe_currency_value\">9.999,00</span>\n                  </b>\n                </div>\n           <p></p>\n      </div>\n                <div class=\"o_wsale_product_btn pl-2\"></div>\n            </div>\n            <span class=\"o_ribbon \" style=\"\"></span>\n        </form>\n                                                        </div>","link":"https://finshop.belgium.be/nl_BE/shop/bxl-01705-2-11783-1-lot-1221-nissan-primastar-67-012-km-diesel-euro-6if-28673","retrieved":1724088794545},{"title":"Lot 1298 BMW K 1200s - 60.041 Km - Benzine","contents":"<div class=\"o_wsale_product_grid_wrapper o_wsale_product_grid_wrapper_1_1\">\n        <form action=\"/nl_BE/shop/cart/update\" method=\"post\" class=\"card oe_product_cart\" itemscope=\"itemscope\" itemtype=\"http://schema.org/Product\" data-publish=\"on\" id=\"product-28676\" title=\"Lot 1298 BMW K 1200s - 60.041 Km - Benzine\">\n            <a class=\"o_product_link css_editable_mode_hidden\" href=\"/nl_BE/shop/bxl-01705-2-11783-2-lot-1298-bmw-k-1200s-60-041-km-benzine-28676\"></a>\n            <div class=\"card-body p-1 oe_product_image\">\n                <input type=\"hidden\" name=\"csrf_token\" value=\"b9e7ff1167226ba50037530fda32a27e197cf42ao1755624793\">\n                <a class=\"d-block h-100\" itemprop=\"url\" href=\"/nl_BE/shop/bxl-01705-2-11783-2-lot-1298-bmw-k-1200s-60-041-km-benzine-28676\">\n                    <span class=\"d-flex h-100 justify-content-center align-items-center\"><img src=\"/web/image/product.template/28676/image_256/%5BBXL-01705-2-11783-2%5D%20Lot%201298%20BMW%20K%201200s%20-%2060.041%20Km%20-%20Benzine?unique=569a8f7\" itemprop=\"image\" class=\"img img-fluid\" alt=\"[BXL/01705/2/11783/2] Lot 1298 BMW K 1200s - 60.041 Km - Benzine\" loading=\"lazy\"></span>\n                </a>\n          <div class=\"product_item auction_running\">\n            <div class=\"col-md-12 card-header border countdown\" style=\"padding:0px\" data-wk_time_left=\"2024-08-22 16:15:00\" data-wk_auction_state=\"running\">\n              <div class=\"row auction_timer\">\n          <div class=\"col-3 text-center\">\n            <span class=\"days span_time_digit\">02</span>\n            <br>\n                        <span class=\"span_time_unit\">Dagen</span>\n          </div>\n          <div class=\"col-3 text-center\">\n            <span class=\"hours span_time_digit\">22</span>\n            <br>\n                        <span class=\"span_time_unit\">Uren</span>\n          </div>\n          <div class=\"col-3 text-center\">\n            <span class=\"minutes span_time_digit\">41</span>\n            <br>\n                        <span class=\"span_time_unit\">Minuten</span>\n          </div>\n          <div class=\"col-3 text-center\">\n            <span class=\"seconds span_time_digit\">46</span>\n            <br>\n                        <span class=\"span_time_unit\">Seconden</span>\n          </div>\n        </div>\n            </div>\n          </div>\n        <div class=\"product_item-warehouse\">\n          <p>Finshop\n            <span class=\"font-weight-bold d-block\">Brussel</span>\n          </p>\n        </div>\n      </div>\n            <div class=\"card-body p-0 o_wsale_product_information\">\n                <div class=\"p-2 o_wsale_product_information_text\">\n                    <h6 class=\"o_wsale_products_item_title mb-1\">\n                        <a class=\"text-primary text-decoration-none text-truncate-2-lines\" itemprop=\"name\" href=\"/nl_BE/shop/bxl-01705-2-11783-2-lot-1298-bmw-k-1200s-60-041-km-benzine-28676\" content=\"Lot 1298 BMW K 1200s - 60.041 Km - Benzine\">Lot 1298 BMW K 1200s - 60.041 Km - Benzine</a>\n                    </h6>\n           <div class=\"text-info oe_subdescription\" contenteditable=\"false\">\n           </div>\n            <p>\n                <span class=\"col-md-4\" style=\"padding-left:0px;padding-right:0px\">\n                  <a class=\"span_total_bids\" href=\"/nl_BE/product/auction/24875\">\n                    1 Biedingen</a>\n                </span>\n                <span style=\"padding-left:0px;padding-right:0px\" class=\"col-md-8 category_page_timer auction_running\">\n                      <span class=\"span_time_digit\">02</span><span class=\"span_time_unit\">d. </span><span class=\"span_time_digit\">22</span><span class=\"span_time_unit\">h. </span><span class=\"span_time_digit\">41</span><span class=\"span_time_unit\">m. </span><span class=\"span_time_digit\">47</span><span class=\"span_time_unit\">s. </span>\n                      <span>&nbsp;&nbsp; left</span>\n                </span>\n                </p><div style=\"position: absolute; bottom: 0; padding: 5px 0; font-size: 14px;\">\n                  <b>\n                    Huidig bod €&nbsp;<span class=\"oe_currency_value\">999,00</span>\n                  </b>\n                </div>\n           <p></p>\n      </div>\n                <div class=\"o_wsale_product_btn pl-2\"></div>\n            </div>\n            <span class=\"o_ribbon \" style=\"\"></span>\n        </form>\n                                                        </div>","link":"https://finshop.belgium.be/nl_BE/shop/bxl-01705-2-11783-2-lot-1298-bmw-k-1200s-60-041-km-benzine-28676","retrieved":1724088794546},{"title":"Lot 1188 Opel Corsa - 121.302 Km - Diesel EURO 6b","contents":"<div class=\"o_wsale_product_grid_wrapper o_wsale_product_grid_wrapper_1_1\">\n        <form action=\"/nl_BE/shop/cart/update\" method=\"post\" class=\"card oe_product_cart\" itemscope=\"itemscope\" itemtype=\"http://schema.org/Product\" data-publish=\"on\" id=\"product-28677\" title=\"Lot 1188 Opel Corsa - 121.302 Km - Diesel EURO 6b\">\n            <a class=\"o_product_link css_editable_mode_hidden\" href=\"/nl_BE/shop/bxl-00002-3-11784-1-lot-1188-opel-corsa-121-302-km-diesel-euro-6b-28677\"></a>\n            <div class=\"card-body p-1 oe_product_image\">\n                <input type=\"hidden\" name=\"csrf_token\" value=\"b9e7ff1167226ba50037530fda32a27e197cf42ao1755624793\">\n                <a class=\"d-block h-100\" itemprop=\"url\" href=\"/nl_BE/shop/bxl-00002-3-11784-1-lot-1188-opel-corsa-121-302-km-diesel-euro-6b-28677\">\n                    <span class=\"d-flex h-100 justify-content-center align-items-center\"><img src=\"/web/image/product.template/28677/image_256/%5BBXL-00002-3-11784-1%5D%20Lot%201188%20Opel%20Corsa%20-%20121.302%20Km%20-%20Diesel%20EURO%206b?unique=27c17af\" itemprop=\"image\" class=\"img img-fluid\" alt=\"[BXL/00002/3/11784/1] Lot 1188 Opel Corsa - 121.302 Km - Diesel EURO 6b\" loading=\"lazy\"></span>\n                </a>\n          <div class=\"product_item auction_running\">\n            <div class=\"col-md-12 card-header border countdown\" style=\"padding:0px\" data-wk_time_left=\"2024-08-22 16:20:00\" data-wk_auction_state=\"running\">\n              <div class=\"row auction_timer\">\n          <div class=\"col-3 text-center\">\n            <span class=\"days span_time_digit\">02</span>\n            <br>\n                        <span class=\"span_time_unit\">Dagen</span>\n          </div>\n          <div class=\"col-3 text-center\">\n            <span class=\"hours span_time_digit\">22</span>\n            <br>\n                        <span class=\"span_time_unit\">Uren</span>\n          </div>\n          <div class=\"col-3 text-center\">\n            <span class=\"minutes span_time_digit\">46</span>\n            <br>\n                        <span class=\"span_time_unit\">Minuten</span>\n          </div>\n          <div class=\"col-3 text-center\">\n            <span class=\"seconds span_time_digit\">46</span>\n            <br>\n                        <span class=\"span_time_unit\">Seconden</span>\n          </div>\n        </div>\n            </div>\n          </div>\n        <div class=\"product_item-warehouse\">\n          <p>Finshop\n            <span class=\"font-weight-bold d-block\">Brussel</span>\n          </p>\n        </div>\n      </div>\n            <div class=\"card-body p-0 o_wsale_product_information\">\n                <div class=\"p-2 o_wsale_product_information_text\">\n                    <h6 class=\"o_wsale_products_item_title mb-1\">\n                        <a class=\"text-primary text-decoration-none text-truncate-2-lines\" itemprop=\"name\" href=\"/nl_BE/shop/bxl-00002-3-11784-1-lot-1188-opel-corsa-121-302-km-diesel-euro-6b-28677\" content=\"Lot 1188 Opel Corsa - 121.302 Km - Diesel EURO 6b\">Lot 1188 Opel Corsa - 121.302 Km - Diesel EURO 6b</a>\n                    </h6>\n           <div class=\"text-info oe_subdescription\" contenteditable=\"false\">\n           </div>\n            <p>\n                <span class=\"col-md-4\" style=\"padding-left:0px;padding-right:0px\">\n                  <a class=\"span_total_bids\" href=\"/nl_BE/product/auction/24877\">\n                    7 Biedingen</a>\n                </span>\n                <span style=\"padding-left:0px;padding-right:0px\" class=\"col-md-8 category_page_timer auction_running\">\n                      <span class=\"span_time_digit\">02</span><span class=\"span_time_unit\">d. </span><span class=\"span_time_digit\">22</span><span class=\"span_time_unit\">h. </span><span class=\"span_time_digit\">46</span><span class=\"span_time_unit\">m. </span><span class=\"span_time_digit\">47</span><span class=\"span_time_unit\">s. </span>\n                      <span>&nbsp;&nbsp; left</span>\n                </span>\n                </p><div style=\"position: absolute; bottom: 0; padding: 5px 0; font-size: 14px;\">\n                  <b>\n                    Huidig bod €&nbsp;<span class=\"oe_currency_value\">3.450,00</span>\n                  </b>\n                </div>\n           <p></p>\n      </div>\n                <div class=\"o_wsale_product_btn pl-2\"></div>\n            </div>\n            <span class=\"o_ribbon \" style=\"\"></span>\n        </form>\n                                                        </div>","link":"https://finshop.belgium.be/nl_BE/shop/bxl-00002-3-11784-1-lot-1188-opel-corsa-121-302-km-diesel-euro-6b-28677","retrieved":1724088794549},{"title":"Lot 1276 BMW 218I - 41.504 Km - Benzine EURO 6if","contents":"<div class=\"o_wsale_product_grid_wrapper o_wsale_product_grid_wrapper_1_1\">\n        <form action=\"/nl_BE/shop/cart/update\" method=\"post\" class=\"card oe_product_cart\" itemscope=\"itemscope\" itemtype=\"http://schema.org/Product\" data-publish=\"on\" id=\"product-28679\" title=\"Lot 1276 BMW 218I - 41.504 Km - Benzine EURO 6if\">\n            <a class=\"o_product_link css_editable_mode_hidden\" href=\"/nl_BE/shop/bxl-00002-3-11785-1-lot-1276-bmw-218i-41-504-km-benzine-euro-6if-28679\"></a>\n            <div class=\"card-body p-1 oe_product_image\">\n                <input type=\"hidden\" name=\"csrf_token\" value=\"b9e7ff1167226ba50037530fda32a27e197cf42ao1755624793\">\n                <a class=\"d-block h-100\" itemprop=\"url\" href=\"/nl_BE/shop/bxl-00002-3-11785-1-lot-1276-bmw-218i-41-504-km-benzine-euro-6if-28679\">\n                    <span class=\"d-flex h-100 justify-content-center align-items-center\"><img src=\"/web/image/product.template/28679/image_256/%5BBXL-00002-3-11785-1%5D%20Lot%201276%20BMW%20218I%20-%2041.504%20Km%20-%20Benzine%20EURO%206if?unique=6c623f3\" itemprop=\"image\" class=\"img img-fluid\" alt=\"[BXL/00002/3/11785/1] Lot 1276 BMW 218I - 41.504 Km - Benzine EURO 6if\" loading=\"lazy\"></span>\n                </a>\n          <div class=\"product_item auction_running\">\n            <div class=\"col-md-12 card-header border countdown\" style=\"padding:0px\" data-wk_time_left=\"2024-08-22 16:25:00\" data-wk_auction_state=\"running\">\n              <div class=\"row auction_timer\">\n          <div class=\"col-3 text-center\">\n            <span class=\"days span_time_digit\">02</span>\n            <br>\n                        <span class=\"span_time_unit\">Dagen</span>\n          </div>\n          <div class=\"col-3 text-center\">\n            <span class=\"hours span_time_digit\">22</span>\n            <br>\n                        <span class=\"span_time_unit\">Uren</span>\n          </div>\n          <div class=\"col-3 text-center\">\n            <span class=\"minutes span_time_digit\">51</span>\n            <br>\n                        <span class=\"span_time_unit\">Minuten</span>\n          </div>\n          <div class=\"col-3 text-center\">\n            <span class=\"seconds span_time_digit\">46</span>\n            <br>\n                        <span class=\"span_time_unit\">Seconden</span>\n          </div>\n        </div>\n            </div>\n          </div>\n        <div class=\"product_item-warehouse\">\n          <p>Finshop\n            <span class=\"font-weight-bold d-block\">Brussel</span>\n          </p>\n        </div>\n      </div>\n            <div class=\"card-body p-0 o_wsale_product_information\">\n                <div class=\"p-2 o_wsale_product_information_text\">\n                    <h6 class=\"o_wsale_products_item_title mb-1\">\n                        <a class=\"text-primary text-decoration-none text-truncate-2-lines\" itemprop=\"name\" href=\"/nl_BE/shop/bxl-00002-3-11785-1-lot-1276-bmw-218i-41-504-km-benzine-euro-6if-28679\" content=\"Lot 1276 BMW 218I - 41.504 Km - Benzine EURO 6if\">Lot 1276 BMW 218I - 41.504 Km - Benzine EURO 6if</a>\n                    </h6>\n           <div class=\"text-info oe_subdescription\" contenteditable=\"false\">\n           </div>\n            <p>\n                <span class=\"col-md-4\" style=\"padding-left:0px;padding-right:0px\">\n                  <a class=\"span_total_bids\" href=\"/nl_BE/product/auction/24878\">\n                    27 Biedingen</a>\n                </span>\n                <span style=\"padding-left:0px;padding-right:0px\" class=\"col-md-8 category_page_timer auction_running\">\n                      <span class=\"span_time_digit\">02</span><span class=\"span_time_unit\">d. </span><span class=\"span_time_digit\">22</span><span class=\"span_time_unit\">h. </span><span class=\"span_time_digit\">51</span><span class=\"span_time_unit\">m. </span><span class=\"span_time_digit\">47</span><span class=\"span_time_unit\">s. </span>\n                      <span>&nbsp;&nbsp; left</span>\n                </span>\n                </p><div style=\"position: absolute; bottom: 0; padding: 5px 0; font-size: 14px;\">\n                  <b>\n                    Huidig bod €&nbsp;<span class=\"oe_currency_value\">17.000,00</span>\n                  </b>\n                </div>\n           <p></p>\n      </div>\n                <div class=\"o_wsale_product_btn pl-2\"></div>\n            </div>\n            <span class=\"o_ribbon \" style=\"\"></span>\n        </form>\n                                                        </div>","link":"https://finshop.belgium.be/nl_BE/shop/bxl-00002-3-11785-1-lot-1276-bmw-218i-41-504-km-benzine-euro-6if-28679","retrieved":1724088794551},{"title":"Lot 1212 Smart ForTwo - 27.770 Km - Benzine EURO 6c","contents":"<div class=\"o_wsale_product_grid_wrapper o_wsale_product_grid_wrapper_1_1\">\n        <form action=\"/nl_BE/shop/cart/update\" method=\"post\" class=\"card oe_product_cart\" itemscope=\"itemscope\" itemtype=\"http://schema.org/Product\" data-publish=\"on\" id=\"product-28682\" title=\"Lot 1212 Smart ForTwo - 27.770 Km - Benzine EURO 6c\">\n            <a class=\"o_product_link css_editable_mode_hidden\" href=\"/nl_BE/shop/bxl-00002-3-11786-1-lot-1212-smart-fortwo-27-770-km-benzine-euro-6c-28682\"></a>\n            <div class=\"card-body p-1 oe_product_image\">\n                <input type=\"hidden\" name=\"csrf_token\" value=\"b9e7ff1167226ba50037530fda32a27e197cf42ao1755624793\">\n                <a class=\"d-block h-100\" itemprop=\"url\" href=\"/nl_BE/shop/bxl-00002-3-11786-1-lot-1212-smart-fortwo-27-770-km-benzine-euro-6c-28682\">\n                    <span class=\"d-flex h-100 justify-content-center align-items-center\"><img src=\"/web/image/product.template/28682/image_256/%5BBXL-00002-3-11786-1%5D%20Lot%201212%20Smart%20ForTwo%20-%2027.770%20Km%20-%20Benzine%20EURO%206c?unique=b4d891b\" itemprop=\"image\" class=\"img img-fluid\" alt=\"[BXL/00002/3/11786/1] Lot 1212 Smart ForTwo - 27.770 Km - Benzine EURO 6c\" loading=\"lazy\"></span>\n                </a>\n          <div class=\"product_item auction_running\">\n            <div class=\"col-md-12 card-header border countdown\" style=\"padding:0px\" data-wk_time_left=\"2024-08-22 16:30:00\" data-wk_auction_state=\"running\">\n              <div class=\"row auction_timer\">\n          <div class=\"col-3 text-center\">\n            <span class=\"days span_time_digit\">02</span>\n            <br>\n                        <span class=\"span_time_unit\">Dagen</span>\n          </div>\n          <div class=\"col-3 text-center\">\n            <span class=\"hours span_time_digit\">22</span>\n            <br>\n                        <span class=\"span_time_unit\">Uren</span>\n          </div>\n          <div class=\"col-3 text-center\">\n            <span class=\"minutes span_time_digit\">56</span>\n            <br>\n                        <span class=\"span_time_unit\">Minuten</span>\n          </div>\n          <div class=\"col-3 text-center\">\n            <span class=\"seconds span_time_digit\">46</span>\n            <br>\n                        <span class=\"span_time_unit\">Seconden</span>\n          </div>\n        </div>\n            </div>\n          </div>\n        <div class=\"product_item-warehouse\">\n          <p>Finshop\n            <span class=\"font-weight-bold d-block\">Brussel</span>\n          </p>\n        </div>\n      </div>\n            <div class=\"card-body p-0 o_wsale_product_information\">\n                <div class=\"p-2 o_wsale_product_information_text\">\n                    <h6 class=\"o_wsale_products_item_title mb-1\">\n                        <a class=\"text-primary text-decoration-none text-truncate-2-lines\" itemprop=\"name\" href=\"/nl_BE/shop/bxl-00002-3-11786-1-lot-1212-smart-fortwo-27-770-km-benzine-euro-6c-28682\" content=\"Lot 1212 Smart ForTwo - 27.770 Km - Benzine EURO 6c\">Lot 1212 Smart ForTwo - 27.770 Km - Benzine EURO 6c</a>\n                    </h6>\n           <div class=\"text-info oe_subdescription\" contenteditable=\"false\">\n           </div>\n            <p>\n                <span class=\"col-md-4\" style=\"padding-left:0px;padding-right:0px\">\n                  <a class=\"span_total_bids\" href=\"/nl_BE/product/auction/24879\">\n                    2 Biedingen</a>\n                </span>\n                <span style=\"padding-left:0px;padding-right:0px\" class=\"col-md-8 category_page_timer auction_running\">\n                      <span class=\"span_time_digit\">02</span><span class=\"span_time_unit\">d. </span><span class=\"span_time_digit\">22</span><span class=\"span_time_unit\">h. </span><span class=\"span_time_digit\">56</span><span class=\"span_time_unit\">m. </span><span class=\"span_time_digit\">47</span><span class=\"span_time_unit\">s. </span>\n                      <span>&nbsp;&nbsp; left</span>\n                </span>\n                </p><div style=\"position: absolute; bottom: 0; padding: 5px 0; font-size: 14px;\">\n                  <b>\n                    Huidig bod €&nbsp;<span class=\"oe_currency_value\">6.900,00</span>\n                  </b>\n                </div>\n           <p></p>\n      </div>\n                <div class=\"o_wsale_product_btn pl-2\"></div>\n            </div>\n            <span class=\"o_ribbon \" style=\"\"></span>\n        </form>\n                                                        </div>","link":"https://finshop.belgium.be/nl_BE/shop/bxl-00002-3-11786-1-lot-1212-smart-fortwo-27-770-km-benzine-euro-6c-28682","retrieved":1724088794553},{"title":"Lot 1213 Mercedes AMG A 45 S - 26.615 Km - Benzine EURO 6if","contents":"<div class=\"o_wsale_product_grid_wrapper o_wsale_product_grid_wrapper_1_1\">\n        <form action=\"/nl_BE/shop/cart/update\" method=\"post\" class=\"card oe_product_cart\" itemscope=\"itemscope\" itemtype=\"http://schema.org/Product\" data-publish=\"on\" id=\"product-28683\" title=\"Lot 1213 Mercedes AMG A 45 S - 26.615 Km - Benzine EURO 6if\">\n            <a class=\"o_product_link css_editable_mode_hidden\" href=\"/nl_BE/shop/bxl-00002-3-11787-1-lot-1213-mercedes-amg-a-45-s-26-615-km-benzine-euro-6if-28683\"></a>\n            <div class=\"card-body p-1 oe_product_image\">\n                <input type=\"hidden\" name=\"csrf_token\" value=\"b9e7ff1167226ba50037530fda32a27e197cf42ao1755624793\">\n                <a class=\"d-block h-100\" itemprop=\"url\" href=\"/nl_BE/shop/bxl-00002-3-11787-1-lot-1213-mercedes-amg-a-45-s-26-615-km-benzine-euro-6if-28683\">\n                    <span class=\"d-flex h-100 justify-content-center align-items-center\"><img src=\"/web/image/product.template/28683/image_256/%5BBXL-00002-3-11787-1%5D%20Lot%201213%20Mercedes%20AMG%20A%2045%20S%20-%2026.615%20Km%20-%20Benzine%20EURO%206if?unique=6d2f19d\" itemprop=\"image\" class=\"img img-fluid\" alt=\"[BXL/00002/3/11787/1] Lot 1213 Mercedes AMG A 45 S - 26.615 Km - Benzine EURO 6if\" loading=\"lazy\"></span>\n                </a>\n          <div class=\"product_item auction_running\">\n            <div class=\"col-md-12 card-header border countdown\" style=\"padding:0px\" data-wk_time_left=\"2024-08-22 16:35:00\" data-wk_auction_state=\"running\">\n              <div class=\"row auction_timer\">\n          <div class=\"col-3 text-center\">\n            <span class=\"days span_time_digit\">02</span>\n            <br>\n                        <span class=\"span_time_unit\">Dagen</span>\n          </div>\n          <div class=\"col-3 text-center\">\n            <span class=\"hours span_time_digit\">23</span>\n            <br>\n                        <span class=\"span_time_unit\">Uren</span>\n          </div>\n          <div class=\"col-3 text-center\">\n            <span class=\"minutes span_time_digit\">01</span>\n            <br>\n                        <span class=\"span_time_unit\">Minuten</span>\n          </div>\n          <div class=\"col-3 text-center\">\n            <span class=\"seconds span_time_digit\">46</span>\n            <br>\n                        <span class=\"span_time_unit\">Seconden</span>\n          </div>\n        </div>\n            </div>\n          </div>\n        <div class=\"product_item-warehouse\">\n          <p>Finshop\n            <span class=\"font-weight-bold d-block\">Brussel</span>\n          </p>\n        </div>\n      </div>\n            <div class=\"card-body p-0 o_wsale_product_information\">\n                <div class=\"p-2 o_wsale_product_information_text\">\n                    <h6 class=\"o_wsale_products_item_title mb-1\">\n                        <a class=\"text-primary text-decoration-none text-truncate-2-lines\" itemprop=\"name\" href=\"/nl_BE/shop/bxl-00002-3-11787-1-lot-1213-mercedes-amg-a-45-s-26-615-km-benzine-euro-6if-28683\" content=\"Lot 1213 Mercedes AMG A 45 S - 26.615 Km - Benzine EURO 6if\">Lot 1213 Mercedes AMG A 45 S - 26.615 Km - Benzine EURO 6if</a>\n                    </h6>\n           <div class=\"text-info oe_subdescription\" contenteditable=\"false\">\n           </div>\n            <p>\n                <span class=\"col-md-4\" style=\"padding-left:0px;padding-right:0px\">\n                  <a class=\"span_total_bids\" href=\"/nl_BE/product/auction/24882\">\n                    6 Biedingen</a>\n                </span>\n                <span style=\"padding-left:0px;padding-right:0px\" class=\"col-md-8 category_page_timer auction_running\">\n                      <span class=\"span_time_digit\">02</span><span class=\"span_time_unit\">d. </span><span class=\"span_time_digit\">23</span><span class=\"span_time_unit\">h. </span><span class=\"span_time_digit\">01</span><span class=\"span_time_unit\">m. </span><span class=\"span_time_digit\">47</span><span class=\"span_time_unit\">s. </span>\n                      <span>&nbsp;&nbsp; left</span>\n                </span>\n                </p><div style=\"position: absolute; bottom: 0; padding: 5px 0; font-size: 14px;\">\n                  <b>\n                    Huidig bod €&nbsp;<span class=\"oe_currency_value\">26.500,00</span>\n                  </b>\n                </div>\n           <p></p>\n      </div>\n                <div class=\"o_wsale_product_btn pl-2\"></div>\n            </div>\n            <span class=\"o_ribbon \" style=\"\"></span>\n        </form>\n                                                        </div>","link":"https://finshop.belgium.be/nl_BE/shop/bxl-00002-3-11787-1-lot-1213-mercedes-amg-a-45-s-26-615-km-benzine-euro-6if-28683","retrieved":1724088794555},{"title":"Lot 1228 Mercedes C 180 - 146.368 Km - Benzine EURO 6dt","contents":"<div class=\"o_wsale_product_grid_wrapper o_wsale_product_grid_wrapper_1_1\">\n        <form action=\"/nl_BE/shop/cart/update\" method=\"post\" class=\"card oe_product_cart\" itemscope=\"itemscope\" itemtype=\"http://schema.org/Product\" data-publish=\"on\" id=\"product-28684\" title=\"Lot 1228 Mercedes C 180 - 146.368 Km - Benzine EURO 6dt\">\n            <a class=\"o_product_link css_editable_mode_hidden\" href=\"/nl_BE/shop/bxl-00002-3-11788-1-lot-1228-mercedes-c-180-146-368-km-benzine-euro-6dt-28684\"></a>\n            <div class=\"card-body p-1 oe_product_image\">\n                <input type=\"hidden\" name=\"csrf_token\" value=\"b9e7ff1167226ba50037530fda32a27e197cf42ao1755624793\">\n                <a class=\"d-block h-100\" itemprop=\"url\" href=\"/nl_BE/shop/bxl-00002-3-11788-1-lot-1228-mercedes-c-180-146-368-km-benzine-euro-6dt-28684\">\n                    <span class=\"d-flex h-100 justify-content-center align-items-center\"><img src=\"/web/image/product.template/28684/image_256/%5BBXL-00002-3-11788-1%5D%20Lot%201228%20Mercedes%20C%20180%20-%20146.368%20Km%20-%20Benzine%20EURO%206dt?unique=e458fce\" itemprop=\"image\" class=\"img img-fluid\" alt=\"[BXL/00002/3/11788/1] Lot 1228 Mercedes C 180 - 146.368 Km - Benzine EURO 6dt\" loading=\"lazy\"></span>\n                </a>\n          <div class=\"product_item auction_running\">\n            <div class=\"col-md-12 card-header border countdown\" style=\"padding:0px\" data-wk_time_left=\"2024-08-22 16:40:00\" data-wk_auction_state=\"running\">\n              <div class=\"row auction_timer\">\n          <div class=\"col-3 text-center\">\n            <span class=\"days span_time_digit\">02</span>\n            <br>\n                        <span class=\"span_time_unit\">Dagen</span>\n          </div>\n          <div class=\"col-3 text-center\">\n            <span class=\"hours span_time_digit\">23</span>\n            <br>\n                        <span class=\"span_time_unit\">Uren</span>\n          </div>\n          <div class=\"col-3 text-center\">\n            <span class=\"minutes span_time_digit\">06</span>\n            <br>\n                        <span class=\"span_time_unit\">Minuten</span>\n          </div>\n          <div class=\"col-3 text-center\">\n            <span class=\"seconds span_time_digit\">46</span>\n            <br>\n                        <span class=\"span_time_unit\">Seconden</span>\n          </div>\n        </div>\n            </div>\n          </div>\n        <div class=\"product_item-warehouse\">\n          <p>Finshop\n            <span class=\"font-weight-bold d-block\">Brussel</span>\n          </p>\n        </div>\n      </div>\n            <div class=\"card-body p-0 o_wsale_product_information\">\n                <div class=\"p-2 o_wsale_product_information_text\">\n                    <h6 class=\"o_wsale_products_item_title mb-1\">\n                        <a class=\"text-primary text-decoration-none text-truncate-2-lines\" itemprop=\"name\" href=\"/nl_BE/shop/bxl-00002-3-11788-1-lot-1228-mercedes-c-180-146-368-km-benzine-euro-6dt-28684\" content=\"Lot 1228 Mercedes C 180 - 146.368 Km - Benzine EURO 6dt\">Lot 1228 Mercedes C 180 - 146.368 Km - Benzine EURO 6dt</a>\n                    </h6>\n           <div class=\"text-info oe_subdescription\" contenteditable=\"false\">\n           </div>\n            <p>\n                <span class=\"col-md-4\" style=\"padding-left:0px;padding-right:0px\">\n                  <a class=\"span_total_bids\" href=\"/nl_BE/product/auction/24883\">\n                    2 Biedingen</a>\n                </span>\n                <span style=\"padding-left:0px;padding-right:0px\" class=\"col-md-8 category_page_timer auction_running\">\n                      <span class=\"span_time_digit\">02</span><span class=\"span_time_unit\">d. </span><span class=\"span_time_digit\">23</span><span class=\"span_time_unit\">h. </span><span class=\"span_time_digit\">06</span><span class=\"span_time_unit\">m. </span><span class=\"span_time_digit\">47</span><span class=\"span_time_unit\">s. </span>\n                      <span>&nbsp;&nbsp; left</span>\n                </span>\n                </p><div style=\"position: absolute; bottom: 0; padding: 5px 0; font-size: 14px;\">\n                  <b>\n                    Huidig bod €&nbsp;<span class=\"oe_currency_value\">9.100,00</span>\n                  </b>\n                </div>\n           <p></p>\n      </div>\n                <div class=\"o_wsale_product_btn pl-2\"></div>\n            </div>\n            <span class=\"o_ribbon \" style=\"\"></span>\n        </form>\n                                                        </div>","link":"https://finshop.belgium.be/nl_BE/shop/bxl-00002-3-11788-1-lot-1228-mercedes-c-180-146-368-km-benzine-euro-6dt-28684","retrieved":1724088794556},{"title":"Lot 1229 Mercedes GLC 220 - 96.990 Km - Diesel EURO 6B","contents":"<div class=\"o_wsale_product_grid_wrapper o_wsale_product_grid_wrapper_1_1\">\n        <form action=\"/nl_BE/shop/cart/update\" method=\"post\" class=\"card oe_product_cart\" itemscope=\"itemscope\" itemtype=\"http://schema.org/Product\" data-publish=\"on\" id=\"product-28685\" title=\"Lot 1229 Mercedes GLC 220 - 96.990 Km - Diesel EURO 6B\">\n            <a class=\"o_product_link css_editable_mode_hidden\" href=\"/nl_BE/shop/bxl-00002-3-11789-1-lot-1229-mercedes-glc-220-96-990-km-diesel-euro-6b-28685\"></a>\n            <div class=\"card-body p-1 oe_product_image\">\n                <input type=\"hidden\" name=\"csrf_token\" value=\"b9e7ff1167226ba50037530fda32a27e197cf42ao1755624793\">\n                <a class=\"d-block h-100\" itemprop=\"url\" href=\"/nl_BE/shop/bxl-00002-3-11789-1-lot-1229-mercedes-glc-220-96-990-km-diesel-euro-6b-28685\">\n                    <span class=\"d-flex h-100 justify-content-center align-items-center\"><img src=\"/web/image/product.template/28685/image_256/%5BBXL-00002-3-11789-1%5D%20Lot%201229%20Mercedes%20GLC%20220%20-%2096.990%20Km%20-%20Diesel%20EURO%206B?unique=8e634ad\" itemprop=\"image\" class=\"img img-fluid\" alt=\"[BXL/00002/3/11789/1] Lot 1229 Mercedes GLC 220 - 96.990 Km - Diesel EURO 6B\" loading=\"lazy\"></span>\n                </a>\n          <div class=\"product_item auction_running\">\n            <div class=\"col-md-12 card-header border countdown\" style=\"padding:0px\" data-wk_time_left=\"2024-08-22 16:45:00\" data-wk_auction_state=\"running\">\n              <div class=\"row auction_timer\">\n          <div class=\"col-3 text-center\">\n            <span class=\"days span_time_digit\">02</span>\n            <br>\n                        <span class=\"span_time_unit\">Dagen</span>\n          </div>\n          <div class=\"col-3 text-center\">\n            <span class=\"hours span_time_digit\">23</span>\n            <br>\n                        <span class=\"span_time_unit\">Uren</span>\n          </div>\n          <div class=\"col-3 text-center\">\n            <span class=\"minutes span_time_digit\">11</span>\n            <br>\n                        <span class=\"span_time_unit\">Minuten</span>\n          </div>\n          <div class=\"col-3 text-center\">\n            <span class=\"seconds span_time_digit\">46</span>\n            <br>\n                        <span class=\"span_time_unit\">Seconden</span>\n          </div>\n        </div>\n            </div>\n          </div>\n        <div class=\"product_item-warehouse\">\n          <p>Finshop\n            <span class=\"font-weight-bold d-block\">Brussel</span>\n          </p>\n        </div>\n      </div>\n            <div class=\"card-body p-0 o_wsale_product_information\">\n                <div class=\"p-2 o_wsale_product_information_text\">\n                    <h6 class=\"o_wsale_products_item_title mb-1\">\n                        <a class=\"text-primary text-decoration-none text-truncate-2-lines\" itemprop=\"name\" href=\"/nl_BE/shop/bxl-00002-3-11789-1-lot-1229-mercedes-glc-220-96-990-km-diesel-euro-6b-28685\" content=\"Lot 1229 Mercedes GLC 220 - 96.990 Km - Diesel EURO 6B\">Lot 1229 Mercedes GLC 220 - 96.990 Km - Diesel EURO 6B</a>\n                    </h6>\n           <div class=\"text-info oe_subdescription\" contenteditable=\"false\">\n           </div>\n            <p>\n                <span class=\"col-md-4\" style=\"padding-left:0px;padding-right:0px\">\n                  <a class=\"span_total_bids\" href=\"/nl_BE/product/auction/24884\">\n                    5 Biedingen</a>\n                </span>\n                <span style=\"padding-left:0px;padding-right:0px\" class=\"col-md-8 category_page_timer auction_running\">\n                      <span class=\"span_time_digit\">02</span><span class=\"span_time_unit\">d. </span><span class=\"span_time_digit\">23</span><span class=\"span_time_unit\">h. </span><span class=\"span_time_digit\">11</span><span class=\"span_time_unit\">m. </span><span class=\"span_time_digit\">46</span><span class=\"span_time_unit\">s. </span>\n                      <span>&nbsp;&nbsp; left</span>\n                </span>\n                </p><div style=\"position: absolute; bottom: 0; padding: 5px 0; font-size: 14px;\">\n                  <b>\n                    Huidig bod €&nbsp;<span class=\"oe_currency_value\">15.000,00</span>\n                  </b>\n                </div>\n           <p></p>\n      </div>\n                <div class=\"o_wsale_product_btn pl-2\"></div>\n            </div>\n            <span class=\"o_ribbon \" style=\"\"></span>\n        </form>\n                                                        </div>","link":"https://finshop.belgium.be/nl_BE/shop/bxl-00002-3-11789-1-lot-1229-mercedes-glc-220-96-990-km-diesel-euro-6b-28685","retrieved":1724088794558},{"title":"Lot 1264 BMW 740 - 151.406 Km - Benzine-elec. EURO6B","contents":"<div class=\"o_wsale_product_grid_wrapper o_wsale_product_grid_wrapper_1_1\">\n        <form action=\"/nl_BE/shop/cart/update\" method=\"post\" class=\"card oe_product_cart\" itemscope=\"itemscope\" itemtype=\"http://schema.org/Product\" data-publish=\"on\" id=\"product-28687\" title=\"Lot 1264 BMW 740 - 151.406 Km - Benzine-elec. EURO6B\">\n            <a class=\"o_product_link css_editable_mode_hidden\" href=\"/nl_BE/shop/bxl-00002-3-11790-1-lot-1264-bmw-740-151-406-km-benzine-elec-euro6b-28687\"></a>\n            <div class=\"card-body p-1 oe_product_image\">\n                <input type=\"hidden\" name=\"csrf_token\" value=\"d7eb46c99aff3a0274fba2d9f83ebca49c3f70a9o1755624794\">\n                <a class=\"d-block h-100\" itemprop=\"url\" href=\"/nl_BE/shop/bxl-00002-3-11790-1-lot-1264-bmw-740-151-406-km-benzine-elec-euro6b-28687\">\n                    <span class=\"d-flex h-100 justify-content-center align-items-center\"><img src=\"/web/image/product.template/28687/image_256/%5BBXL-00002-3-11790-1%5D%20Lot%201264%20BMW%20740%20-%20151.406%20Km%20-%20Benzine-elec.%20EURO6B?unique=001f7d5\" itemprop=\"image\" class=\"img img-fluid\" alt=\"[BXL/00002/3/11790/1] Lot 1264 BMW 740 - 151.406 Km - Benzine-elec. EURO6B\" loading=\"lazy\"></span>\n                </a>\n          <div class=\"product_item auction_running\">\n            <div class=\"col-md-12 card-header border countdown\" style=\"padding:0px\" data-wk_time_left=\"2024-08-22 16:50:00\" data-wk_auction_state=\"running\">\n              <div class=\"row auction_timer\">\n          <div class=\"col-3 text-center\">\n            <span class=\"days span_time_digit\">02</span>\n            <br>\n                        <span class=\"span_time_unit\">Dagen</span>\n          </div>\n          <div class=\"col-3 text-center\">\n            <span class=\"hours span_time_digit\">23</span>\n            <br>\n                        <span class=\"span_time_unit\">Uren</span>\n          </div>\n          <div class=\"col-3 text-center\">\n            <span class=\"minutes span_time_digit\">16</span>\n            <br>\n                        <span class=\"span_time_unit\">Minuten</span>\n          </div>\n          <div class=\"col-3 text-center\">\n            <span class=\"seconds span_time_digit\">45</span>\n            <br>\n                        <span class=\"span_time_unit\">Seconden</span>\n          </div>\n        </div>\n            </div>\n          </div>\n        <div class=\"product_item-warehouse\">\n          <p>Finshop\n            <span class=\"font-weight-bold d-block\">Brussel</span>\n          </p>\n        </div>\n      </div>\n            <div class=\"card-body p-0 o_wsale_product_information\">\n                <div class=\"p-2 o_wsale_product_information_text\">\n                    <h6 class=\"o_wsale_products_item_title mb-1\">\n                        <a class=\"text-primary text-decoration-none text-truncate-2-lines\" itemprop=\"name\" href=\"/nl_BE/shop/bxl-00002-3-11790-1-lot-1264-bmw-740-151-406-km-benzine-elec-euro6b-28687\" content=\"Lot 1264 BMW 740 - 151.406 Km - Benzine-elec. EURO6B\">Lot 1264 BMW 740 - 151.406 Km - Benzine-elec. EURO6B</a>\n                    </h6>\n           <div class=\"text-info oe_subdescription\" contenteditable=\"false\">\n           </div>\n            <p>\n                <span class=\"col-md-4\" style=\"padding-left:0px;padding-right:0px\">\n                  <a class=\"span_total_bids\" href=\"/nl_BE/product/auction/24885\">\n                    2 Biedingen</a>\n                </span>\n                <span style=\"padding-left:0px;padding-right:0px\" class=\"col-md-8 category_page_timer auction_running\">\n                      <span class=\"span_time_digit\">02</span><span class=\"span_time_unit\">d. </span><span class=\"span_time_digit\">23</span><span class=\"span_time_unit\">h. </span><span class=\"span_time_digit\">16</span><span class=\"span_time_unit\">m. </span><span class=\"span_time_digit\">46</span><span class=\"span_time_unit\">s. </span>\n                      <span>&nbsp;&nbsp; left</span>\n                </span>\n                </p><div style=\"position: absolute; bottom: 0; padding: 5px 0; font-size: 14px;\">\n                  <b>\n                    Huidig bod €&nbsp;<span class=\"oe_currency_value\">13.200,00</span>\n                  </b>\n                </div>\n           <p></p>\n      </div>\n                <div class=\"o_wsale_product_btn pl-2\"></div>\n            </div>\n            <span class=\"o_ribbon \" style=\"\"></span>\n        </form>\n                                                        </div>","link":"https://finshop.belgium.be/nl_BE/shop/bxl-00002-3-11790-1-lot-1264-bmw-740-151-406-km-benzine-elec-euro6b-28687","retrieved":1724088794559}]}